crossinstaller/__init__.py
crossinstaller/__main__.py
crossinstaller/config.py
crossinstaller/exceptions.py
crossinstaller/generator.py
crossinstaller/platform.py
crossinstaller/Docker/Dockerfile-py3-amd64
crossinstaller/Docker/Dockerfile-py3-i386
crossinstaller/Docker/Dockerfile-py3-win32
crossinstaller/Docker/Dockerfile-py3-win64
crossinstaller/Docker/entrypoint-linux.sh
crossinstaller/Docker/entrypoint-windows.sh
crossinstaller-0.2.0.dist-info/LICENSE
crossinstaller-0.2.0.dist-info/METADATA
crossinstaller-0.2.0.dist-info/WHEEL
crossinstaller-0.2.0.dist-info/entry_points.txt
crossinstaller-0.2.0.dist-info/top_level.txt
crossinstaller-0.2.0.dist-info/RECORD
