Metadata-Version: 2.1
Name: crossinstaller
Version: 0.2.0
Summary: PyInstaller + Docker = CrossInstaller
Home-page: https://github.com/desty2k/crossinstaller
Author: Wojciech Wentland
Author-email: wojciech.wentland@int.pl
License: MIT
Keywords: packaging,app,apps,bundle,convert,standalone,executable,pyinstaller,cxfreeze,freeze,py2exe,py2app,bbfreeze,docker
Platform: UNKNOWN
Classifier: Development Status :: 3 - Alpha
Classifier: Environment :: Console
Classifier: License :: OSI Approved :: MIT License
Classifier: Programming Language :: Python
Classifier: Programming Language :: Python :: 3
Classifier: Programming Language :: Python :: 3 :: Only
Classifier: Programming Language :: Python :: 3.9
Classifier: Programming Language :: Python :: Implementation :: CPython
Classifier: Intended Audience :: Developers
Classifier: Intended Audience :: Other Audience
Classifier: Intended Audience :: System Administrators
Classifier: Intended Audience :: Information Technology
Classifier: Topic :: Software Development
Classifier: Topic :: Software Development :: Build Tools
Classifier: Topic :: Software Development :: Interpreters
Classifier: Topic :: Software Development :: Libraries :: Python Modules
Classifier: Topic :: System :: Installation/Setup
Classifier: Topic :: System :: Software Distribution
Classifier: Topic :: Utilities
Requires-Python: >=3.9
License-File: LICENSE
Requires-Dist: docker
